pynyu/__init__.py
pynyu/hello.py
pynyu-0.0.3.dist-info/LICENSE
pynyu-0.0.3.dist-info/METADATA
pynyu-0.0.3.dist-info/WHEEL
pynyu-0.0.3.dist-info/top_level.txt
pynyu-0.0.3.dist-info/RECORD
